pyshellscript/__init__.py
pyshellscript/local_command_executor.py
pyshellscript/remote_command_executor.py
pyshellscript/utils.py
pyshellscript-0.1.1.dist-info/LICENSE
pyshellscript-0.1.1.dist-info/METADATA
pyshellscript-0.1.1.dist-info/WHEEL
pyshellscript-0.1.1.dist-info/RECORD
