Metadata-Version: 2.1
Name: pyshellscript
Version: 0.1.1
Summary: 
License: MIT
Author: Dawid Kalicki
Requires-Python: >=3.12,<4.0
Classifier: License :: OSI Approved :: MIT License
Classifier: Programming Language :: Python :: 3
Classifier: Programming Language :: Python :: 3.12
Requires-Dist: loguru (>=0.7.2,<0.8.0)
Requires-Dist: paramiko (>=3.4.0,<4.0.0)
